signal_tl/_cext.cpython-38-i386-linux-gnu.so
signal_tl/__init__.py
signal_temporal_logic-0.1.3.post1.dist-info/WHEEL
signal_temporal_logic-0.1.3.post1.dist-info/RECORD
signal_temporal_logic-0.1.3.post1.dist-info/METADATA
signal_temporal_logic-0.1.3.post1.dist-info/LICENSE-3rdParty
signal_temporal_logic-0.1.3.post1.dist-info/top_level.txt
