Metadata-Version: 2.1
Name: signal-temporal-logic
Version: 0.1.3.post1
Summary: A library for efficiently working with Signal Temporal Logic (STL) and its quantitative semantics.
Home-page: https://github.com/anand-bala/signal-temporal-logic
Author: Anand Balakrishnan
Author-email: anandbala1597@gmail.com
License: UNKNOWN
Platform: UNKNOWN
Classifier: Programming Language :: Python :: 3 :: Only
Classifier: Programming Language :: Python :: 3.5
Classifier: Programming Language :: Python :: 3.6
Classifier: Programming Language :: Python :: 3.7
Classifier: Programming Language :: Python :: 3.8
Classifier: Programming Language :: C++
Classifier: License :: OSI Approved :: MIT License
Classifier: Intended Audience :: Science/Research
Requires-Python: ==3.*,>=3.5
